[
  {
    "title": "☎️ TelKo",
    "url": "//calendar.google.com/calendar/embed?src=ka4n8q2876sap90kpikqp493kk%40group.calendar.google.com&ctz=Europe%2FBerlin"
  },
  {
    "title": "Jugend",
    "url": "//calendar.google.com/calendar/embed?src=jugend%40johannische-kirche.org&ctz=Europe%2FBerlins"
  },
  {
    "title": "SMH",
    "url": "//calendar.google.com/calendar/embed?src=41cva8imqg9f443kn41dul8onc%40group.calendar.google.com&ctz=Europe%2FBerlin"
  },
  {
    "title": "Velten",
    "url": "//calendar.google.com/calendar/embed?src=90k02p9ir853ts5ks5hanilpfg%40group.calendar.google.com&ctz=Europe%2FBerlin"
  },
  {
    "title": "Urgemeinde",
    "url": "//calendar.google.com/calendar/embed?src=2ma7gn9d8sa5j6ekin4pkhnm4k%40group.calendar.google.com&ctz=Europe%2FBerlin"
  },
  {
    "title": "Chor",
    "url": "//calendar.google.com/calendar/embed?src=c009ps9dpfhds19bjapr6lvte0%40group.calendar.google.com&ctz=Europe%2FBerlin"
  }
]
